chroma_datasets/__init__.py
chroma_datasets/types.py
chroma_datasets/utils.py
chroma_datasets/__pycache__/__init__.cpython-310.pyc
chroma_datasets/datasets/glue.py
chroma_datasets/datasets/huberman_podcast.py
chroma_datasets/datasets/paul_graham_essay.py
chroma_datasets/datasets/sciq.py
chroma_datasets/datasets/state_of_the_union.py
chroma_datasets-0.1.5.dist-info/LICENSE.md
chroma_datasets-0.1.5.dist-info/METADATA
chroma_datasets-0.1.5.dist-info/WHEEL
chroma_datasets-0.1.5.dist-info/top_level.txt
chroma_datasets-0.1.5.dist-info/RECORD
