Metadata-Version: 2.1
Name: chroma-datasets
Version: 0.1.5
Summary: Chroma Datasets - easy to use datasets for vector retrieval
Author-email: Jeff Huber <jeff@trychroma.com>, Anton Troynikov <anton@trychroma.com>
Project-URL: Homepage, https://github.com/chroma-core/chroma-datasets
Project-URL: Bug Tracker, https://github.com/chroma-core/chromachroma-datasets/issues
Classifier: Programming Language :: Python :: 3
Classifier: License :: OSI Approved :: Apache Software License
Classifier: Operating System :: OS Independent
Requires-Python: >=3.7
License-File: LICENSE.md
Requires-Dist: langchain
Requires-Dist: datasets
